{"name":"MVPet's Github Page","tagline":"","body":"### Welcome to MVPet's Github Page\r\nThis is the page where all my major projects are hosted.\r\nThe source is available to download and all projects are playable.\r\n\r\n\r\n### Projects are:\r\n\r\n### Megaman Battle Chip Challenge Battle Arena\r\nA fan made game I made to test out Unity 2D.\r\n\r\n[http://mvpet.github.io/MMBNNE/](http://mvpet.github.io/MMBNNE/)\r\n\r\n### 3D Game Thing\r\nA playground used for testing out 3D game development.\r\nWas done with Unity3D and is continuously updated.\r\n\r\n[http://mvpet.github.io/3DThing](http://mvpet.github.io/3DThing)\r\n\r\n### Buoyancy Simulation\r\nA project I am currently lead for at ITMS at URI.\r\nWas done with Unity3D and is continuously updated.\r\n\r\n[http://mvpet.github.io/OceanPhysics](http://mvpet.github.io/OceanPhysics)\r\n\r\n### Hunger Game\r\nA project I did for the Nutrition department at URI\r\nWas done with ActionScript3 and Flixel.\r\n\r\n[http://mvpet.github.io/GreenEating](http://mvpet.github.io/GreenEating)\r\n\r\n\r\n","google":"","note":"Don't delete this file! It's used internally to help with page regeneration."}